pysparkcli/__init__.py
pysparkcli/bin/__init__.py
pysparkcli/bin/start.py
pysparkcli/core/__init__.py
pysparkcli/core/utils.py
pysparkcli/core/admin/__init__.py
pysparkcli/project-template/default/project_name/src/__init__.py-tpl
pysparkcli/project-template/default/project_name/src/app.py-tpl
pysparkcli/project-template/default/project_name/src/configs/__init__.py-tpl
pysparkcli/project-template/default/project_name/src/configs/etl_config.json
pysparkcli/project-template/default/project_name/src/jobs/__init__.py-tpl
pysparkcli/project-template/default/project_name/src/jobs/etl_job.py-tpl
pysparkcli/project-template/default/project_name/src/settings/__init__.py-tpl
pysparkcli/project-template/default/project_name/src/settings/default.py-tpl
pysparkcli/project-template/default/project_name/src/settings/local.py-tpl
pysparkcli/project-template/default/project_name/src/settings/production.py-tpl
pysparkcli/project-template/default/project_name/tests/__init__.py
pysparkcli/project-template/default/project_name/tests/test_etl_job.py
pysparkcli/project-template/default/project_name/tests/test_data/employees/part-00000-9abf32a3-db43-42e1-9639-363ef11c0d1c-c000.snappy.parquet
pysparkcli/project-template/default/project_name/tests/test_data/employees_report/part-00000-4a609ba3-0404-48bb-bb22-2fec3e2f1e68-c000.snappy.parquet
pysparkcli/project-template/project_name/src/__init__.py-tpl
pysparkcli/project-template/project_name/src/app.py-tpl
pysparkcli/project-template/project_name/src/configs/__init__.py-tpl
pysparkcli/project-template/project_name/src/configs/etl_config.json
pysparkcli/project-template/project_name/src/jobs/__init__.py-tpl
pysparkcli/project-template/project_name/src/jobs/etl_job.py-tpl
pysparkcli/project-template/project_name/src/settings/__init__.py-tpl
pysparkcli/project-template/project_name/src/settings/default.py-tpl
pysparkcli/project-template/project_name/src/settings/local.py-tpl
pysparkcli/project-template/project_name/src/settings/production.py-tpl
pyspark_cli-1.0.1.dist-info/LICENSE
pyspark_cli-1.0.1.dist-info/METADATA
pyspark_cli-1.0.1.dist-info/WHEEL
pyspark_cli-1.0.1.dist-info/entry_points.txt
pyspark_cli-1.0.1.dist-info/top_level.txt
pyspark_cli-1.0.1.dist-info/RECORD
