Metadata-Version: 2.1
Name: pyspark-cli
Version: 1.0.1
Summary: PySpark Project Buiding Tool
Home-page: https://github.com/qburst/PySparkCLI
Author: Jino Jossy
Author-email: jinojossy93@gmail.com
License: MIT
Platform: UNKNOWN
Requires-Dist: pyspark
Requires-Dist: click
Requires-Dist: jinja2
Requires-Dist: pathlib (>1.0.0)
